wumpy/cache/__init__.py
wumpy/cache/_protocol.py
wumpy/cache/py.typed
wumpy/cache/in_memory/__init__.py
wumpy/cache/in_memory/_base.py
wumpy/cache/in_memory/_channel.py
wumpy/cache/in_memory/_guild.py
wumpy/cache/in_memory/_user.py
wumpy_cache-0.1.0.dist-info/WHEEL
wumpy_cache-0.1.0.dist-info/METADATA
wumpy_cache-0.1.0.dist-info/RECORD
